rest_framework/__init__.py
rest_framework/exceptions.py
rest_framework/serializers/__init__.py
rest_framework/serializers/exceptions.py
rest_framework/serializers/fields.py
rest_framework/serializers/helpers.py
rest_framework/serializers/serializers.py
rest_framework/serializers/validators.py
rest_framework/tests/__init__.py
rest_framework/tests/serializers_for_tests.py
rest_framework/tests/test_fields.py
rest_framework/tests/test_serializers.py
rest_framework/tests/test_validators.py
rest_framework/utils/__init__.py
rest_framework/utils/collections.py
rest_framework/utils/html.py
Python_Rest_Framework-0.1.7.dist-info/LICENSE
Python_Rest_Framework-0.1.7.dist-info/METADATA
Python_Rest_Framework-0.1.7.dist-info/WHEEL
Python_Rest_Framework-0.1.7.dist-info/top_level.txt
Python_Rest_Framework-0.1.7.dist-info/RECORD
