Metadata-Version: 2.1
Name: Python-Rest-Framework
Version: 0.1.7
Summary: Python Rest Framework. Box utils for easy makes rest api on python
Home-page: https://github.com/nxexox/python-rest-framework
Author: Deys Timofey
Author-email: nxexox@gmail.com
Maintainer: Deys Timofey
Maintainer-email: nxexox@gmail.com
License: Apache 2.0
Platform: UNKNOWN
Classifier: Environment :: Web Environment
Classifier: Intended Audience :: Developers
Classifier: License :: OSI Approved :: Apache Software License
Classifier: Operating System :: OS Independent
Classifier: Programming Language :: Python
Classifier: Programming Language :: Python :: 3
Classifier: Programming Language :: Python :: 3.3
Classifier: Programming Language :: Python :: 3.4
Classifier: Programming Language :: Python :: 3.5
Classifier: Programming Language :: Python :: 3.6
Classifier: Topic :: Internet :: WWW/HTTP
Classifier: Topic :: Internet :: WWW/HTTP :: Dynamic Content
Requires-Dist: six (>=1)
